librgbd.so
pyrgbd.cpython-37m-x86_64-linux-gnu.so
pyrgbd-0.1.2.dist-info/METADATA
pyrgbd-0.1.2.dist-info/LICENSE
pyrgbd-0.1.2.dist-info/RECORD
pyrgbd-0.1.2.dist-info/top_level.txt
pyrgbd-0.1.2.dist-info/WHEEL
