Metadata-Version: 2.1
Name: pyrgbd
Version: 0.1.2
Summary: Library for reading and writing RGBD videos.
License-File: LICENSE
Requires-Dist: numpy
Requires-Dist: pyglm
